{"name":"Júlio Prestes","url":"/wiki/J%C3%BAlio_Prestes","Born":"","Died":"1946-02-09","Political party":"PRP","termEnds":"(PRB)","termStarts":null,"text":"Júlio Prestes de Albuquerque (Portuguese pronunciation: [ˈʒulju ˈpɾɛstʃiz dʒi awbuˈkɛɾki]; 15 March 1882 \u2013 9 February 1946) was a Brazilian poet, lawyer and politician. He was the last elected President of Brazil of the period known as the Old Republic, but never took office because the government was overthrown in the Revolution of 1930. Prestes was the only politician to be elected President of Brazil and then impeded from taking office.[1] He was also the last person born in São Paulo to be elected president until the election of Jair Bolsonaro in 2018. On June 23, 1930, he became the second Brazilian featured on the cover of Time magazine.[2] Prestes graduated with a law degree from the Law School of São Paulo (today the Faculty of Law of the University of São Paulo) in 1906. He married Alice Viana Prestes and had three children with her. He started his political career in 1909, when he was elected State Representative in São Paulo by the Republican Party of São Paulo (PRP). He was re-elected several times until 1923, and became noted for his defense of the public employee in São Paulo. As a State Representative, he introduced legislation that created the Court of Auditors of São Paulo and the Faculty of Veterinary Medicine and Zootechnology of the University of São Paulo. He was the author of the law that incorporated the Sorocabana Railroad in the São Paulo State patrimony. In the Revolution of 1924, Prestes fought on the Coluna Sul, with Ataliba Leonel and Washington Luís, expelling the rebels of the region of Sorocaba. This article about a Brazilian politician is a stub. You can help Wikipedia by expanding it.","country":"Brazil"}